youtubetogo/__init__.py
youtubetogo/main.py
youtubetogo-0.1.3.dist-info/LICENSE
youtubetogo-0.1.3.dist-info/METADATA
youtubetogo-0.1.3.dist-info/WHEEL
youtubetogo-0.1.3.dist-info/entry_points.txt
youtubetogo-0.1.3.dist-info/top_level.txt
youtubetogo-0.1.3.dist-info/RECORD
